INSTALL.rst
LICENSE
MANIFEST.in
README.rst
VERSION
requirements.txt
setup.cfg
setup.py
tasks.py
src/qlcompiler/__init__.py
src/qlcompiler/__meta__.py
src/qlcompiler/c_compiler.py
src/qlcompiler/compiler.py
src/qlcompiler/js_compiler.py
src/qlcompiler/py_compiler.py
src/qlcompiler.egg-info/PKG-INFO
src/qlcompiler.egg-info/SOURCES.txt
src/qlcompiler.egg-info/dependency_links.txt
src/qlcompiler.egg-info/not-zip-safe
src/qlcompiler.egg-info/requires.txt
src/qlcompiler.egg-info/top_level.txt
src/qlcompiler/tests/__init__.py
src/qlcompiler/tests/test_documentation.py
src/qlcompiler/tests/test_py_compiler.py
src/qlcompiler/tests/test_qlcompiler.py